improc/__init__.py
improc/filtering.py
improc/multifiletiff.py
improc/segfunctions.py
improc/NPproc/__init__.py
improc/NPproc/eval/__init__.py
improc/NPproc/eval/eval.py
improc/NPproc/process/__init__.py
improc/NPproc/process/atlas.py
improc/NPproc/process/file.py
improc/NPproc/process/histogram.py
improc/NPproc/process/resample.py
improc/NPproc/utils/__init__.py
improc/NPproc/utils/utils.py
improc/NPproc/visualize/__init__.py
improc/NPproc/visualize/visualize.py
foco_improc-0.0.0.dist-info/METADATA
foco_improc-0.0.0.dist-info/WHEEL
foco_improc-0.0.0.dist-info/top_level.txt
foco_improc-0.0.0.dist-info/RECORD
