Metadata-Version: 2.1
Name: foco-improc
Version: 0.0.0
Summary: standalone repository for image processing algorithm implementations
Home-page: 
Author: UCSF FOCO Lab
Author-email: focolabdev@gmail.com
Classifier: Programming Language :: Python :: 3
Classifier: License :: OSI Approved :: MIT License
Classifier: Operating System :: OS Independent
Requires-Python: >=3.6
Requires-Dist: numpy
Requires-Dist: scipy
Requires-Dist: opencv-python-headless
Requires-Dist: scikit-image
Requires-Dist: matplotlib
Requires-Dist: pandas
Requires-Dist: tifffile
Requires-Dist: pynwb
Requires-Dist: matlab
